fastafurious/__init__.py
fastafurious/__main__.py
fastafurious/compare.py
fastafurious/composition.py
fastafurious/filter.py
fastafurious/rename.py
fastafurious/subset.py
fastafurious/version.py
fastafurious-1.2.5.dist-info/METADATA
fastafurious-1.2.5.dist-info/WHEEL
fastafurious-1.2.5.dist-info/entry_points.txt
fastafurious-1.2.5.dist-info/top_level.txt
fastafurious-1.2.5.dist-info/RECORD
