Metadata-Version: 2.1
Name: fastafurious
Version: 1.2.5
Summary: Bundled utilities for manipulating and integrating FASTA files
Home-page: https://github.com/matt-sd-watson/FASTAfurious/
Author: Matthew Watson
Author-email: matthew.watson@uhn.ca
License: UNKNOWN
Project-URL: Issues, https://github.com/matt-sd-watson/FASTAfurious/issues
Project-URL: Source, https://github.com/matt-sd-watson/FASTAfurious
Platform: UNKNOWN
Requires-Dist: pandas (>=1.1.5)
Requires-Dist: numpy (>=1.19)
Requires-Dist: biopython (>=1.79)
Requires-Dist: pypandoc (>=1.8)
Requires-Dist: pytest (>=7.1.2)
